promptstream/__init__.py
promptstream/client.py
promptstream/exceptions.py
promptstream/models.py
promptstream-0.1.3.dist-info/licenses/LICENSE
promptstream-0.1.3.dist-info/METADATA
promptstream-0.1.3.dist-info/WHEEL
promptstream-0.1.3.dist-info/top_level.txt
promptstream-0.1.3.dist-info/RECORD
