Metadata-Version: 2.4
Name: promptstream
Version: 0.1.3
Summary: SDK for interacting with the PromptStream API
Author-email: PromptStream <hello@promptstream.ai>
License: MIT License
Project-URL: Homepage, https://promptstream.ai
Project-URL: Docs, https://docs.promptstream.ai
Requires-Python: >=3.8
License-File: LICENSE
Requires-Dist: httpx
Requires-Dist: pydantic
Dynamic: license-file
